kanirequests/__init__.py
kanirequests-0.1.0.dist-info/DESCRIPTION.rst
kanirequests-0.1.0.dist-info/METADATA
kanirequests-0.1.0.dist-info/RECORD
kanirequests-0.1.0.dist-info/WHEEL
kanirequests-0.1.0.dist-info/metadata.json
kanirequests-0.1.0.dist-info/top_level.txt
tests/__init__.py
tests/test_sample.py
